src/__init__.py
src/app.py
src/main.py
mflux_streamlit-0.0.1.dist-info/LICENSE.md
mflux_streamlit-0.0.1.dist-info/METADATA
mflux_streamlit-0.0.1.dist-info/WHEEL
mflux_streamlit-0.0.1.dist-info/entry_points.txt
mflux_streamlit-0.0.1.dist-info/top_level.txt
mflux_streamlit-0.0.1.dist-info/RECORD
